{
  "run_id": "carbon_20260224_162633",
  "retrained_any_model": false,
  "baseline_total_annual_cost_usd": 51231688.364929505,
  "top_mitigation_by_npv": "Combined Portfolio",
  "top_mitigation_npv_10y_usd": 55823069.969902165,
  "max_forecast_annual_cost_usd": 505420788.0969089,
  "max_forecast_annual_cost_scenario": "Aggressive 30%",
  "max_forecast_annual_cost_year": 2035,
  "outputs": [
    "analysis_manifest.json",
    "carbon_intensity_heatmap.csv",
    "carbon_intensity_heatmap.svg",
    "copula_energy_tail_bars.svg",
    "copula_tail_curves.csv",
    "copula_tail_dashboard.svg",
    "copula_tail_dependence.csv",
    "energy_forecast_costs.csv",
    "energy_forecast_costs.svg",
    "energy_forecast_scenarios.csv",
    "financial_assumptions.csv",
    "mitigation_cost_benefit.csv",
    "mitigation_npv_payback.svg",
    "monetary_numbers.csv",
    "monetizable_outcomes_dashboard.svg",
    "recommendation_energy_peak_projection.svg",
    "recommendation_mitigation.csv",
    "recommendation_mitigation_impact.svg",
    "recommendation_scenario_radar.svg",
    "recommendation_scenarios.csv",
    "risk_premium_breakdown.csv",
    "scenario_carbon_price_band.svg",
    "scenario_cost_stack.svg",
    "scenario_monetization.csv",
    "sensitivity_visual_report.md",
    "sobol_energy_sensitivity.svg",
    "sobol_global_sensitivity.svg",
    "sobol_indices.csv",
    "sobol_indices_energy.csv",
    "tornado_oat.csv",
    "tornado_oat_emissions.svg",
    "tornado_oat_energy.csv",
    "tornado_oat_energy.svg"
  ]
}